{
  "display": {
    "icon": {
      "item": "japaricraftmod:darksandstar"
    },
    "title": {
      "translate": "advancements.japaricraftmod.starsorcerger.title"
    },
    "description": {
      "translate": "advancements.japaricraftmod.starsorcerger.description"
    },
    "frame": "challenge"
  },
  "parent": "japaricraftmod:japaricraftmod/cerulean",
  "criteria": {
    "starsorcerger": {
      "trigger": "minecraft:player_killed_entity",
      "conditions": {
        "entity": {
          "type": "japaricraftmod:starsorcerger"
        }
      }
    }
  },
  "requirements": [
    [
      "starsorcerger"
    ]
  ],
  "rewards": {
    "experience": 100
  }
}